cloudwatch_alarm_to_slack/__init__.py
cloudwatch_alarm_to_slack/entrypoint.py
cloudwatch_alarm_to_slack/errors/__init__.py
cloudwatch_alarm_to_slack/events/__init__.py
cloudwatch_alarm_to_slack/events/cloudwatch.py
cloudwatch_alarm_to_slack/events/slack.py
cloudwatch_alarm_to_slack/models/__init__.py
cloudwatch_alarm_to_slack/models/cloudwatch.py
cloudwatch_alarm_to_slack/templates/__init__.py
cloudwatch_alarm_to_slack/templates/slack.py
cloudwatch_alarm_to_slack/utils/__init__.py
cloudwatch_alarm_to_slack/utils/log.py
tests/__init__.py
tests/conftest.py
tests/test_notifier.py
tests/events/__init__.py
tests/events/test_cloudwatch.py
tests/events/test_slack_event.py
tests/templates/__init__.py
tests/templates/test_slack_templates.py
cloudwatch_alarm_to_slack-1.0.0.dist-info/AUTHORS.md
cloudwatch_alarm_to_slack-1.0.0.dist-info/LICENSE
cloudwatch_alarm_to_slack-1.0.0.dist-info/METADATA
cloudwatch_alarm_to_slack-1.0.0.dist-info/WHEEL
cloudwatch_alarm_to_slack-1.0.0.dist-info/top_level.txt
cloudwatch_alarm_to_slack-1.0.0.dist-info/RECORD
