Metadata-Version: 2.1
Name: cloudwatch-alarm-to-slack
Version: 1.0.0
Summary: A python library to send cloudwatch alarm events from sns to slack
Home-page: https://github.com/jpdhas/cloudwatch_alarm_to_slack
Author: Jermila Paul Dhas
Author-email: dhas.jermila@gmail.com
License: MIT license
Keywords: cloudwatch_alarm_to_slack,cloudwatchalarm,sns,slack,lambda
Platform: UNKNOWN
Classifier: Development Status :: 5 - Production/Stable
Classifier: Intended Audience :: Developers
Classifier: Natural Language :: English
Classifier: License :: OSI Approved :: MIT License
Classifier: Programming Language :: Python :: 3 :: Only
Classifier: Programming Language :: Python :: 3.6
Classifier: Programming Language :: Python :: 3.7
Classifier: Programming Language :: Python :: 3.8
Classifier: Programming Language :: Python :: Implementation :: CPython
Classifier: Programming Language :: Python :: Implementation :: PyPy
Classifier: Operating System :: OS Independent
Classifier: Programming Language :: Python
Classifier: Topic :: Software Development
Requires-Python: >=3.6
Requires-Dist: slack-sdk
Requires-Dist: pydantic
